mipac/__init__.py
mipac/_version.py
mipac/client.py
mipac/config.py
mipac/file.py
mipac/http.py
mipac/abstract/__init__.py
mipac/abstract/action.py
mipac/abstract/manager.py
mipac/actions/__init__.py
mipac/actions/antenna.py
mipac/actions/app.py
mipac/actions/blocking.py
mipac/actions/channel.py
mipac/actions/chart.py
mipac/actions/client.py
mipac/actions/clip.py
mipac/actions/emoji.py
mipac/actions/favorite.py
mipac/actions/federation.py
mipac/actions/follow.py
mipac/actions/hashtag.py
mipac/actions/invite.py
mipac/actions/my.py
mipac/actions/note.py
mipac/actions/poll.py
mipac/actions/reaction.py
mipac/actions/role.py
mipac/actions/user.py
mipac/actions/username.py
mipac/actions/admins/__init__.py
mipac/actions/admins/accounts.py
mipac/actions/admins/ad.py
mipac/actions/admins/admin.py
mipac/actions/admins/announcement.py
mipac/actions/admins/drive.py
mipac/actions/admins/emoji.py
mipac/actions/admins/invite.py
mipac/actions/admins/roles.py
mipac/actions/admins/user.py
mipac/actions/drive/drive.py
mipac/actions/drive/files.py
mipac/actions/drive/folders.py
mipac/actions/users/__init__.py
mipac/actions/users/list.py
mipac/actions/users/mute.py
mipac/errors/__init__.py
mipac/errors/base.py
mipac/errors/errors.py
mipac/manager/__init__.py
mipac/manager/antenna.py
mipac/manager/app.py
mipac/manager/blocking.py
mipac/manager/channel.py
mipac/manager/chart.py
mipac/manager/client.py
mipac/manager/clip.py
mipac/manager/emoji.py
mipac/manager/favorite.py
mipac/manager/federation.py
mipac/manager/follow.py
mipac/manager/hashtag.py
mipac/manager/invite.py
mipac/manager/my.py
mipac/manager/note.py
mipac/manager/page.py
mipac/manager/poll.py
mipac/manager/reaction.py
mipac/manager/role.py
mipac/manager/user.py
mipac/manager/username.py
mipac/manager/admins/__init__.py
mipac/manager/admins/accounts.py
mipac/manager/admins/ad.py
mipac/manager/admins/admin.py
mipac/manager/admins/announcement.py
mipac/manager/admins/drive.py
mipac/manager/admins/emoji.py
mipac-0.7.4.dist-info/LICENSE
mipac-0.7.4.dist-info/METADATA
mipac-0.7.4.dist-info/WHEEL
mipac-0.7.4.dist-info/top_level.txt
mipac-0.7.4.dist-info/RECORD
