Metadata-Version: 2.1
Name: mipac
Version: 0.7.4
Summary: A Python wrapper for the Misskey API
Home-page: https://github.com/yupix/mipac
Author: yupix
Author-email: yupi0982@outlook.jp
License: MIT
Classifier: Development Status :: 2 - Pre-Alpha
Classifier: Programming Language :: Python :: 3.12
Classifier: Natural Language :: Japanese
Classifier: License :: OSI Approved :: MIT License
Requires-Python: >=3.12, <4.0
License-File: LICENSE
Requires-Dist: aiohttp ==3.9.1
Requires-Dist: versioneer
Provides-Extra: ci
Requires-Dist: mypy ; extra == 'ci'
Requires-Dist: ruff ; extra == 'ci'
Provides-Extra: dev
Requires-Dist: isort ; extra == 'dev'
Requires-Dist: mypy ; extra == 'dev'
Requires-Dist: pre-commit ; extra == 'dev'
Requires-Dist: ruff ; extra == 'dev'
Provides-Extra: doc
Requires-Dist: sphinx ; extra == 'doc'
Requires-Dist: furo ; extra == 'doc'
Requires-Dist: sphinxcontrib-trio ; extra == 'doc'
Requires-Dist: sphinx-intl ; extra == 'doc'
Requires-Dist: numpydoc ; extra == 'doc'
Provides-Extra: speed
Requires-Dist: orjson ; extra == 'speed'
